fast_shape_finder.cpython-38-aarch64-linux-gnu.so
fast_shape_finder-1.0.0a1.dist-info/top_level.txt
fast_shape_finder-1.0.0a1.dist-info/METADATA
fast_shape_finder-1.0.0a1.dist-info/WHEEL
fast_shape_finder-1.0.0a1.dist-info/RECORD
fast_shape_finder-1.0.0a1.dist-info/LICENSE
