Metadata-Version: 2.1
Name: fast-shape-finder
Version: 1.0.0a1
Summary: Finding simple geometric shapes quickly using RANSAC-based algorithms
Author: Tolga Demirdal
License: GNU GENERAL PUBLIC LICENSE
Project-URL: Homepage, https://github.com/shadymeowy/fast-shape-finder
Project-URL: Repository, https://github.com/shadymeowy/fast-shape-finder
License-File: LICENSE
Requires-Dist: numpy
